{"title":"Welcome","date":"2018-09-27T12:52:10.000Z","excerpt":"","slug":"Welcome","updated":"2018-09-27T12:53:01.000Z","content":"","next":{"title":"Hello World","slug":"hello-world"},"link":"http://yoursite.com/2018/09/27/Welcome/","copyright":{"author":"Sairshee","license":"Attribution-NonCommercial-NoDerivatives 4.0 International (<a href=\\\"https://creativecommons.org/licenses/by-nc-sa/4.0/\\\" rel=\\\"external nofollow noopener\\\" target=\\\"_blank\\\">CC BY-NC-ND 4.0</a>)","published":"September 27, 2018"}}